ptinsearcher/__init__.py
ptinsearcher/_version.py
ptinsearcher/ptinsearcher.py
ptinsearcher/modules/__init__.py
ptinsearcher/modules/_files_scraper.py
ptinsearcher/modules/_website_scraper.py
ptinsearcher/modules/comments.py
ptinsearcher/modules/emails.py
ptinsearcher/modules/forms.py
ptinsearcher/modules/ip_addresses.py
ptinsearcher/modules/metadata.py
ptinsearcher/modules/phone_numbers.py
ptinsearcher/modules/phones.py
ptinsearcher/modules/urls.py
ptinsearcher/modules/cli/__init__.py
ptinsearcher/modules/cli/args_validator.py
ptinsearcher/modules/cli/extract_flags.py
ptinsearcher/modules/results/__init__.py
ptinsearcher/modules/results/base_result.py
ptinsearcher/modules/results/results.py
ptinsearcher/modules/scraping/__init__.py
ptinsearcher/modules/scraping/google.py
ptinsearcher/modules/scraping/re_search.py
ptinsearcher-1.0.34.dist-info/licenses/LICENSE
ptinsearcher-1.0.34.dist-info/METADATA
ptinsearcher-1.0.34.dist-info/WHEEL
ptinsearcher-1.0.34.dist-info/entry_points.txt
ptinsearcher-1.0.34.dist-info/top_level.txt
ptinsearcher-1.0.34.dist-info/RECORD
